{
  "name": "create_lead",
  "description": "Any new lead that is created in the CRM",
  "parameters": {
    "type": "object",
    "properties": {
      "name": { "type": "string", "description": "The name of the lead" },
      "email": { "type": "string", "format": "email", "description": "The email address of the lead" },
      "phone": { "type": "string", "description": "The phone number of the lead" },
      "company": { "type": ["string","null"], "description": "The company of the lead" },
      "notes": { "type": ["string","null"], "description": "Any additional notes about the lead" }
    },
    "required": ["name","email","phone"]
  }
}
